testcoverage/_version.pyi
testcoverage/a.py
testcoverage/_core.pyi
testcoverage/_core.cpython-311-x86_64-linux-gnu.so
testcoverage/_version.py
testcoverage/py.typed
testcoverage/__init__.py
testcoverage/lib/libCoverageControl.so
testcoverage/lib/cmake/CoverageControl/CoverageControlConfigVersion.cmake
testcoverage/lib/cmake/CoverageControl/CoverageControlTargets-release.cmake
testcoverage/lib/cmake/CoverageControl/CoverageControlConfig.cmake
testcoverage/lib/cmake/CoverageControl/CoverageControlTargets.cmake
testcoverage/nn/__init__.py
testcoverage/nn/models/cnn_backbone.py
testcoverage/nn/models/gnn_backbone.py
testcoverage/nn/models/cnn.py
testcoverage/nn/models/config_parser.py
testcoverage/nn/models/gnn.py
testcoverage/nn/models/__init__.py
testcoverage/nn/utils/coverage_system.py
testcoverage/nn/utils/__init__.py
testcoverage/nn/utils/to_tensor.py
testcoverage/nn/data_loaders/data_loaders.py
testcoverage/nn/data_loaders/__init__.py
testcoverage/nn/data_loaders/data_loader_utils.py
testcoverage/nn/trainers/multi_trainer.py
testcoverage/nn/trainers/trainer.py
testcoverage/nn/trainers/__init__.py
testcoverage/core/__init__.py
testcoverage/include/CoverageControl/vec2d.h
testcoverage/include/CoverageControl/coverage_system.h
testcoverage/include/CoverageControl/constants.h
testcoverage/include/CoverageControl/world_idf.h
testcoverage/include/CoverageControl/typedefs.h
testcoverage/include/CoverageControl/robot_model.h
testcoverage/include/CoverageControl/cuda_utils.h
testcoverage/include/CoverageControl/geographiclib_wrapper.h
testcoverage/include/CoverageControl/Config.h
testcoverage/include/CoverageControl/plotter.h
testcoverage/include/CoverageControl/parameters.h
testcoverage/include/CoverageControl/map_utils.h
testcoverage/include/CoverageControl/bivariate_normal_distribution.h
testcoverage/include/CoverageControl/voronoi.h
testcoverage/include/CoverageControl/generate_world_map.h
testcoverage-0.3.7.dist-info/WHEEL
testcoverage-0.3.7.dist-info/RECORD
testcoverage-0.3.7.dist-info/entry_points.txt
testcoverage-0.3.7.dist-info/METADATA
testcoverage-0.3.7.dist-info/licenses/LICENSE
