Metadata-Version: 2.1
Name: testcoverage
Version: 0.3.7
Summary: A great package.
Author-Email: Saurav Agarwal <agr.saurav1@gmail.com>
License:                     GNU GENERAL PUBLIC LICENSE
Classifier: Development Status :: 4 - Beta
Classifier: Intended Audience :: Science/Research
Classifier: Intended Audience :: Education
Classifier: License :: OSI Approved :: GNU General Public License v3 (GPLv3)
Classifier: Operating System :: OS Independent
Classifier: Programming Language :: C++
Classifier: Programming Language :: Python :: 3
Classifier: Framework :: Robot Framework
Classifier: Topic :: Scientific/Engineering :: Artificial Intelligence
Classifier: Environment :: GPU :: NVIDIA CUDA
Project-URL: Homepage, https://github.com/agarwalsaurav/TestCC
Project-URL: Bug tracker, https://github.com/agarwalsaurav/TestCC/issues
Project-URL: Discussions, https://github.com/agarwalsaurav/TestCC/discussions
Project-URL: Changelog, https://github.com/agarwalsaurav/TestCC/releases
Requires-Python: >=3.10
Requires-Dist: numpy
License-File: LICENSE
